PythonWuJianduXuexiShiyongZhinanChuyiFix1/README.md
PythonWuJianduXuexiShiyongZhinanChuyiFix1/__init__.py
PythonWuJianduXuexiShiyongZhinanChuyiFix1/__main__.py
PythonWuJianduXuexiShiyongZhinanChuyiFix1/file.epub
PythonWuJianduXuexiShiyongZhinanChuyiFix1/index.html
PythonWuJianduXuexiShiyongZhinanChuyiFix1/css/__init__.py
PythonWuJianduXuexiShiyongZhinanChuyiFix1/css/annotations.css
PythonWuJianduXuexiShiyongZhinanChuyiFix1/css/main.css
PythonWuJianduXuexiShiyongZhinanChuyiFix1/css/normalize.css
PythonWuJianduXuexiShiyongZhinanChuyiFix1/css/popup.css
PythonWuJianduXuexiShiyongZhinanChuyiFix1/font/__init__.py
PythonWuJianduXuexiShiyongZhinanChuyiFix1/font/fontello.eot
PythonWuJianduXuexiShiyongZhinanChuyiFix1/font/fontello.svg
PythonWuJianduXuexiShiyongZhinanChuyiFix1/font/fontello.ttf
PythonWuJianduXuexiShiyongZhinanChuyiFix1/font/fontello.woff
PythonWuJianduXuexiShiyongZhinanChuyiFix1/img/__init__.py
PythonWuJianduXuexiShiyongZhinanChuyiFix1/img/annotator-glyph-sprite.png
PythonWuJianduXuexiShiyongZhinanChuyiFix1/img/annotator-icon-sprite.png
PythonWuJianduXuexiShiyongZhinanChuyiFix1/img/apple-touch-icon.png
PythonWuJianduXuexiShiyongZhinanChuyiFix1/img/cancelfullscreen.png
PythonWuJianduXuexiShiyongZhinanChuyiFix1/img/close.png
PythonWuJianduXuexiShiyongZhinanChuyiFix1/img/fullscreen.png
PythonWuJianduXuexiShiyongZhinanChuyiFix1/img/loader.gif
PythonWuJianduXuexiShiyongZhinanChuyiFix1/img/menu-icon.png
PythonWuJianduXuexiShiyongZhinanChuyiFix1/img/save.png
PythonWuJianduXuexiShiyongZhinanChuyiFix1/img/saved.png
PythonWuJianduXuexiShiyongZhinanChuyiFix1/img/settings-s.png
PythonWuJianduXuexiShiyongZhinanChuyiFix1/img/settings.png
PythonWuJianduXuexiShiyongZhinanChuyiFix1/img/star.png
PythonWuJianduXuexiShiyongZhinanChuyiFix1/js/__init__.py
PythonWuJianduXuexiShiyongZhinanChuyiFix1/js/epub.js
PythonWuJianduXuexiShiyongZhinanChuyiFix1/js/epub.min.js
PythonWuJianduXuexiShiyongZhinanChuyiFix1/js/epub.min.map
PythonWuJianduXuexiShiyongZhinanChuyiFix1/js/hooks.min.js
python_wu_jiandu_xuexi_shiyong_zhinan_chuyi_fix1-2025.3.24.1.dist-info/METADATA
python_wu_jiandu_xuexi_shiyong_zhinan_chuyi_fix1-2025.3.24.1.dist-info/WHEEL
python_wu_jiandu_xuexi_shiyong_zhinan_chuyi_fix1-2025.3.24.1.dist-info/entry_points.txt
python_wu_jiandu_xuexi_shiyong_zhinan_chuyi_fix1-2025.3.24.1.dist-info/top_level.txt
python_wu_jiandu_xuexi_shiyong_zhinan_chuyi_fix1-2025.3.24.1.dist-info/RECORD
